odoo/addons/sm_rest_capture_log/README.md
odoo/addons/sm_rest_capture_log/__init__.py
odoo/addons/sm_rest_capture_log/__manifest__.py
odoo/addons/sm_rest_capture_log/controllers/__init__.py
odoo/addons/sm_rest_capture_log/controllers/rest_interceptor.py
odoo/addons/sm_rest_capture_log/models/__init__.py
odoo/addons/sm_rest_capture_log/models/rest_replay_config.py
odoo/addons/sm_rest_capture_log/models/rest_request_log.py
odoo/addons/sm_rest_capture_log/security/ir.model.access.csv
odoo/addons/sm_rest_capture_log/tools/migration_helper.py
odoo/addons/sm_rest_capture_log/tools/replay_to_odoo17.py
odoo/addons/sm_rest_capture_log/views/rest_replay_config_views.xml
odoo/addons/sm_rest_capture_log/views/rest_request_log_views.xml
odoo/addons/sm_rest_capture_log/wizards/__init__.py
odoo/addons/sm_rest_capture_log/wizards/replay_requests_wizard.py
odoo/addons/sm_rest_capture_log/wizards/replay_requests_wizard_views.xml
odoo12_addon_sm_rest_capture_log-12.0.1.0.0.dist-info/METADATA
odoo12_addon_sm_rest_capture_log-12.0.1.0.0.dist-info/WHEEL
odoo12_addon_sm_rest_capture_log-12.0.1.0.0.dist-info/top_level.txt
odoo12_addon_sm_rest_capture_log-12.0.1.0.0.dist-info/RECORD
