Metadata-Version: 2.1
Name: odoo12-addon-sm-rest-capture-log
Version: 12.0.1.0.0
Summary: Temporary module to capture and log all REST API requests during Odoo 12 to 17 migration
Home-page: https://www.sommobilitat.coop
Author: Som Mobilitat
License: UNKNOWN
Platform: UNKNOWN
Classifier: Programming Language :: Python
Classifier: Framework :: Odoo
Classifier: Framework :: Odoo :: 12.0
Classifier: Development Status :: 3 - Alpha
Requires-Python: >=3.5
Requires-Dist: odoo12-addon-base-rest
Requires-Dist: odoo <12.1dev,>=12.0a
